tp_mongo/main.py
tp_mongo_09c77c38_19e1_42d9_886a_42a530ba9064-0.0.1.dist-info/METADATA
tp_mongo_09c77c38_19e1_42d9_886a_42a530ba9064-0.0.1.dist-info/WHEEL
tp_mongo_09c77c38_19e1_42d9_886a_42a530ba9064-0.0.1.dist-info/top_level.txt
tp_mongo_09c77c38_19e1_42d9_886a_42a530ba9064-0.0.1.dist-info/RECORD
