Metadata-Version: 2.1
Name: tp_mongo_09c77c38-19e1-42d9-886a-42a530ba9064
Version: 0.0.1
Requires-Dist: dnspython
Requires-Dist: pymongo[srv]
